icds_data_definitions/__init__.py
icds_data_definitions/aerial_corridor/__init__.py
icds_data_definitions/aerial_corridor/v1/__init__.py
icds_data_definitions/aerial_corridor/v1/corridor_booking_schema.py
icds_data_definitions/aerial_corridor/v1/drone_port_schema.py
icds_data_definitions/aerial_corridor/v1/dss.py
icds_data_definitions/aerial_corridor/v1/schema.py
icds_data_definitions/common/__init__.py
icds_data_definitions/common/v1/__init__.py
icds_data_definitions/common/v1/schema.py
icds_data_definitions-0.0.24.dist-info/METADATA
icds_data_definitions-0.0.24.dist-info/WHEEL
icds_data_definitions-0.0.24.dist-info/top_level.txt
icds_data_definitions-0.0.24.dist-info/RECORD
