Metadata-Version: 2.1
Name: icds_data_definitions
Version: 0.0.24
Summary: Data definitions for IC Discovery Services as Pydantic objects
Home-page: https://github.com/openskies-sh/icds_data_definitions
Download-URL: https://pypi.org/project/icds_data_definitions/
Author: Dr. Hrishikesh Ballal
Author-email: hrishikeshballal@yahoo.com
License: Apache-2.0
Keywords: ICDS
Requires-Dist: pydantic==2.9.2
Requires-Dist: pre-commit==4.0.1
